README.md
setup.cfg
setup.py
TOPSIS_Rohan_101803151_v08.egg-info/PKG-INFO
TOPSIS_Rohan_101803151_v08.egg-info/SOURCES.txt
TOPSIS_Rohan_101803151_v08.egg-info/dependency_links.txt
TOPSIS_Rohan_101803151_v08.egg-info/requires.txt
TOPSIS_Rohan_101803151_v08.egg-info/top_level.txt
topsis/__init__.py
topsis/__main__.py