Metadata-Version: 2.1
Name: TOPSIS-Rohan-101803151-v08
Version: 1.0.8
Summary: A package that makes it easy to create Pypi packages
Home-page: https://github.com/duttrohan0302/TOPSIS-Rohan-101803151
Author: Rohan Dutt
Author-email: duttrohan0302@gmail.com
License: UNKNOWN
Download-URL: https://github.com/duttrohan0302/TOPSIS-Rohan-101803151/archive/v_08.tar.gz
Platform: UNKNOWN
Classifier: Programming Language :: Python :: 3
Classifier: License :: OSI Approved :: MIT License
Classifier: Operating System :: OS Independent
